things_eeg2_dataset/__init__.py
things_eeg2_dataset/paths.py
things_eeg2_dataset/cli/__init__.py
things_eeg2_dataset/cli/logger.py
things_eeg2_dataset/cli/main.py
things_eeg2_dataset/cli/profiling.py
things_eeg2_dataset/cli/show.py
things_eeg2_dataset/dataloader/README.md
things_eeg2_dataset/dataloader/__init__.py
things_eeg2_dataset/dataloader/data_config.json
things_eeg2_dataset/dataloader/datamodule.py
things_eeg2_dataset/dataloader/dataset.py
things_eeg2_dataset/dataloader/dataset_new.py
things_eeg2_dataset/dataloader/sample_info.py
things_eeg2_dataset/processing/__init__.py
things_eeg2_dataset/processing/download_processed.sh
things_eeg2_dataset/processing/download_raw.sh
things_eeg2_dataset/processing/pipeline.py
things_eeg2_dataset/processing/downloading/__init__.py
things_eeg2_dataset/processing/downloading/download_utils.py
things_eeg2_dataset/processing/downloading/downloader.py
things_eeg2_dataset/processing/eeg_processing/__init__.py
things_eeg2_dataset/processing/eeg_processing/epoching.py
things_eeg2_dataset/processing/eeg_processing/raw_processor.py
things_eeg2_dataset/processing/eeg_processing/save.py
things_eeg2_dataset/processing/eeg_processing/whiten.py
things_eeg2_dataset/processing/embedding_processing/__init__.py
things_eeg2_dataset/processing/embedding_processing/embedding_generators.py
things_eeg2_dataset/processing/embedding_processing/embedding_models/__init__.py
things_eeg2_dataset/processing/embedding_processing/embedding_models/ip_adapter/__init__.py
things_eeg2_dataset/processing/embedding_processing/embedding_models/ip_adapter/attention_processor.py
things_eeg2_dataset/processing/embedding_processing/embedding_models/ip_adapter/attention_processor_faceid.py
things_eeg2_dataset/processing/embedding_processing/embedding_models/ip_adapter/custom_pipelines.py
things_eeg2_dataset/processing/embedding_processing/embedding_models/ip_adapter/ip_adapter.py
things_eeg2_dataset-0.0.3.dist-info/METADATA
things_eeg2_dataset-0.0.3.dist-info/WHEEL
things_eeg2_dataset-0.0.3.dist-info/entry_points.txt
things_eeg2_dataset-0.0.3.dist-info/licenses/LICENSE
things_eeg2_dataset-0.0.3.dist-info/RECORD
