Metadata-Version: 2.4
Name: things_eeg2_dataset
Version: 0.0.3
Summary: A simple and fast CLI for downloading, processing, and loading the THINGS-EEG2 dataset.
License: # Creative Commons Attribution-NonCommercial 4.0 International
License-File: LICENSE
Requires-Python: >=3.10
Requires-Dist: accelerate>=1.12.0
Requires-Dist: diffusers>=0.35.2
Requires-Dist: einops>=0.8.1
Requires-Dist: gdown>=5.2.0
Requires-Dist: lightning>=2.6.0
Requires-Dist: mne>=1.11.0
Requires-Dist: osfclient>=0.0.5
Requires-Dist: pandas>=2.3.3
Requires-Dist: plotly>=6.5.0
Requires-Dist: pyinstrument>=5.1.1
Requires-Dist: safetensors>=0.6.2
Requires-Dist: scikit-learn>=1.7.2
Requires-Dist: streamlit>=1.52.1
Requires-Dist: torchvision>=0.24.1
Requires-Dist: transformers>=4.57.1
Requires-Dist: typer>=0.20.0
